setup.py
pypred/__init__.py
pypred/ast.py
pypred/cache.py
pypred/compact.py
pypred/compare.py
pypred/contains.py
pypred/merge.py
pypred/optimizer.py
pypred/parser.py
pypred/parsetab.py
pypred/predicate.py
pypred/set.py
pypred/tiler.py
pypred/util.py
pypred.egg-info/PKG-INFO
pypred.egg-info/SOURCES.txt
pypred.egg-info/dependency_links.txt
pypred.egg-info/requires.txt
pypred.egg-info/top_level.txt