Metadata-Version: 1.0
Name: pypred
Version: 0.3.6
Summary: A Python library for simple evaluation of natural language predicates
Home-page: https://github.com/armon/pypred/
Author: Armon Dadgar
Author-email: armon@kiip.me
License: MIT License
Keywords: python,predicate,natural language
Platform: UNKNOWN
Classifier: Development Status :: 4 - Beta
Classifier: Intended Audience :: Developers
Classifier: License :: OSI Approved :: MIT License
Classifier: Operating System :: POSIX
Classifier: Programming Language :: Python
Classifier: Topic :: Software Development :: Libraries
